stratify/__init__.py
stratify/_bounded_vinterp.py
stratify/_conservative.c
stratify/_conservative.cp311-win_amd64.pyd
stratify/_conservative.pyx
stratify/_version.py
stratify/_vinterp.c
stratify/_vinterp.cp311-win_amd64.pyd
stratify/_vinterp.pyx
stratify/tests/__init__.py
stratify/tests/performance.py
stratify/tests/test_bounded_vinterp.py
stratify/tests/test_vinterp.py
stratify-0.4.0.dist-info/licenses/LICENSE
stratify-0.4.0.dist-info/METADATA
stratify-0.4.0.dist-info/WHEEL
stratify-0.4.0.dist-info/top_level.txt
stratify-0.4.0.dist-info/RECORD
