Metadata-Version: 2.4
Name: stratify
Version: 0.4.0
Summary: Vectorized interpolators for Nd atmospheric and oceanographic data
Author-email: Stratify Contributors <scitools.pub@gmail.com>
License-Expression: BSD-3-Clause
Project-URL: Code, https://github.com/SciTools-incubator/python-stratify
Project-URL: Issues, https://github.com/SciTools-incubator/python-stratify/issues
Keywords: atmospheric-science,cython,interpolation,numpy,python,ocean-science
Classifier: Development Status :: 5 - Production/Stable
Classifier: Intended Audience :: Science/Research
Classifier: Operating System :: POSIX
Classifier: Operating System :: POSIX :: Linux
Classifier: Operating System :: Unix
Classifier: Programming Language :: Python
Classifier: Programming Language :: Python :: 3 :: Only
Classifier: Programming Language :: Python :: 3.11
Classifier: Programming Language :: Python :: 3.12
Classifier: Programming Language :: Python :: 3.13
Classifier: Programming Language :: Python :: Implementation :: CPython
Classifier: Topic :: Scientific/Engineering
Classifier: Topic :: Scientific/Engineering :: Atmospheric Science
Requires-Python: >=3.11
License-File: LICENSE
Requires-Dist: Cython>=3.1.0
Requires-Dist: dask[array]>=2025.7.0
Requires-Dist: numpy>=2
Dynamic: license-file
